MoDE_embeddings/MoDE.py
MoDE_embeddings/__init__.py
MoDE_embeddings/benchmark_MoDE.py
MoDE_embeddings/metrics.py
MoDE_embeddings/waterfilling_compression.py
MoDE_embeddings/fastgd/__init__.py
MoDE_embeddings/fastgd/bootstrap.c
MoDE_embeddings/fastgd/bootstrap.cpython-39-x86_64-linux-gnu.so
MoDE_embeddings/fastgd/bootstrap.pyx
MoDE_embeddings/fastgd/fastgd_base.c
MoDE_embeddings/fastgd/fastgd_base.cpython-39-x86_64-linux-gnu.so
MoDE_embeddings/fastgd/fastgd_base.pyx
MoDE_embeddings/fastgd/fastgd_cython.c
MoDE_embeddings/fastgd/fastgd_cython.cpython-39-x86_64-linux-gnu.so
MoDE_embeddings/fastgd/fastgd_cython.pyx
MoDE_embeddings/fastgd/fastgd_faster.c
MoDE_embeddings/fastgd/fastgd_faster.cpython-39-x86_64-linux-gnu.so
MoDE_embeddings/fastgd/fastgd_faster.pyx
MoDE_embeddings-0.1.5.dist-info/LICENSE
MoDE_embeddings-0.1.5.dist-info/METADATA
MoDE_embeddings-0.1.5.dist-info/WHEEL
MoDE_embeddings-0.1.5.dist-info/top_level.txt
MoDE_embeddings-0.1.5.dist-info/RECORD
