Metadata-Version: 2.1
Name: MoDE_embeddings
Version: 0.1.5
Summary: Source code for Multi-objective Data embeddings
Author-email: Ahmad Ajalloeian <ajal.ahmad@gmail.com>
Project-URL: Homepage, https://github.com/ahmadajal/MoDE/tree/master/Python_implementation
Project-URL: Bug Tracker, https://github.com/ahmadajal/MoDE/issues
Classifier: Programming Language :: Python :: 3
Classifier: License :: OSI Approved :: MIT License
Classifier: Operating System :: OS Independent
Requires-Python: >=3.7
License-File: LICENSE
Requires-Dist: numpy >=1.20.3
Requires-Dist: scipy >=1.7.1
Requires-Dist: scikit-learn >=0.24.2
Requires-Dist: matplotlib >=3.4.3
